ggdrive-0.1.4.data/scripts/gdrive
modules/__init__.py
modules/backports.py
modules/chunks.py
modules/command.py
modules/config.py
modules/extractor.py
modules/googleservice.py
modules/logger.py
modules/progresslogger.py
modules/util.py
ggdrive-0.1.4.dist-info/LICENSE
ggdrive-0.1.4.dist-info/METADATA
ggdrive-0.1.4.dist-info/WHEEL
ggdrive-0.1.4.dist-info/top_level.txt
ggdrive-0.1.4.dist-info/RECORD
