Metadata-Version: 2.1
Name: ggdrive
Version: 0.1.4
Summary: A command-line tool for operating on Google Drive directly from the terminal.
Home-page: https://github.com/DiscordTime/ggdrive
Author: DiscordTime
License: UNKNOWN
Platform: UNKNOWN
Classifier: Programming Language :: Python
Classifier: Programming Language :: Python :: 3
Classifier: Programming Language :: Python :: 3 :: Only
Classifier: Programming Language :: Python :: 3.6
Classifier: Programming Language :: Python :: 3.7
Classifier: Programming Language :: Python :: 3.8
Classifier: Programming Language :: Python :: 3.9
Classifier: License :: OSI Approved :: MIT License
Classifier: Operating System :: OS Independent
Classifier: Topic :: Software Development :: Libraries :: Python Modules
Requires-Python: >=3.6
License-File: LICENSE
Requires-Dist: google-api-python-client
Requires-Dist: google-auth-httplib2
Requires-Dist: google-auth-oauthlib
Requires-Dist: contextvars ; python_version == "3.6"
Requires-Dist: dataclasses ; python_version == "3.6"
